howard/__init__.py
howard/main.py
howard/functions/__init__.py
howard/functions/commons.VV.py
howard/functions/commons.py
howard/functions/databases.py
howard/functions/from_annovar.py
howard/functions/from_extann.py
howard/functions/plugins.py
howard/functions/utils.py
howard/objects/__init__.py
howard/objects/cdna.py
howard/objects/database copy 2.py
howard/objects/database copy.py
howard/objects/database.py
howard/objects/genome.py
howard/objects/hgvs.py
howard/objects/transcript.py
howard/objects/variant.py
howard/objects/variants.VV.py
howard/objects/variants.ok_but_to_clean.py
howard/objects/variants.py
howard/objects/variants.test_stream.py
howard/tools/__init__.py
howard/tools/annotation.py
howard/tools/calculation.py
howard/tools/convert.py
howard/tools/databases.py
howard/tools/filter.py
howard/tools/gui.py
howard/tools/help.py
howard/tools/hgvs.py
howard/tools/interactive.py
howard/tools/prioritization.py
howard/tools/process copy.py
howard/tools/process.py
howard/tools/process_multi copy.py
howard/tools/query.py
howard/tools/sort.py
howard/tools/stats.py
howard/tools/tools.py
plugins/__init__.py
plugins/genebe/__init__.py
plugins/genebe/__main__.py
plugins/minimalize/__init__.py
plugins/minimalize/__main__.py
plugins/show_plugin/__init__.py
plugins/show_plugin/__main__.py
plugins/to_excel/__init__.py
plugins/to_excel/__main__.py
plugins/transcripts_check/__init__.py
plugins/transcripts_check/__main__.py
plugins/update_database/__init__.py
plugins/update_database/__main__.py
plugins/update_database/alphamissence.py
plugins/update_database/cadd.py
plugins/update_database/clinvar.py
plugins/update_database/factory.py
plugins/update_database/gnomad.py
plugins/update_database/mistic.py
plugins/update_database/omim.py
plugins/update_database/ucsc.py
plugins/update_database/utils.py
pyhoward-0.13.0.dist-info/LICENSE
pyhoward-0.13.0.dist-info/METADATA
pyhoward-0.13.0.dist-info/WHEEL
pyhoward-0.13.0.dist-info/entry_points.txt
pyhoward-0.13.0.dist-info/top_level.txt
pyhoward-0.13.0.dist-info/RECORD
