Metadata-Version: 2.1
Name: pyhoward
Version: 0.13.0
Summary: HOWARD - Highly Open Workflow for Annotation & Ranking toward genomic variant Discovery
Home-page: https://github.com/bioinfo-chru-strasbourg/howard
Author: Antony Le Bechec, Jean-Baptiste Lamouche
Author-email: bioinfo@chru-strasbourg.fr
Keywords: VCF,variant,annotation,ranking
Classifier: Programming Language :: Python :: 3.10
Classifier: License :: OSI Approved :: GNU Affero General Public License v3
Classifier: Operating System :: OS Independent
Requires-Python: <3.11,>=3.10
License-File: LICENSE
Requires-Dist: pandas~=2.2.0
Requires-Dist: duckdb~=1.0.0
Requires-Dist: pyarrow~=16.1.0
Requires-Dist: bio~=1.7.0
Requires-Dist: pyvcf3~=1.0.0
Requires-Dist: dask~=2023.12.0
Requires-Dist: pytest~=8.2.0
Requires-Dist: coverage~=7.5.0
Requires-Dist: fastparquet~=2024.5.0
Requires-Dist: polars~=0.20.0
Requires-Dist: genomepy~=0.16.0
Requires-Dist: flake8~=7.1.0
Requires-Dist: lazy~=1.6.0
Requires-Dist: pynose~=1.5.0
Requires-Dist: pyfaidx~=0.8.0
Requires-Dist: multiprocesspandas~=1.1.0
Requires-Dist: bgzip~=0.4.0
Requires-Dist: pgzip~=0.3.0
Requires-Dist: mgzip~=0.2.0
Requires-Dist: pysam~=0.22.0
Requires-Dist: jproperties~=2.1.0
Requires-Dist: psutil~=6.0.0
Requires-Dist: markdown~=3.6.0
Requires-Dist: tabulate~=0.9.0
Requires-Dist: md-toc~=9.0.0
Requires-Dist: numpy~=1.26.0
Requires-Dist: beautifulsoup4~=4.12.0
Requires-Dist: pyBigWig~=0.3.0
Requires-Dist: cyvcf2~=0.31.0
Requires-Dist: pypandoc-binary~=1.14.0
Requires-Dist: pyfiglet~=1.0.0
Requires-Dist: termcolor~=2.5.0
Requires-Dist: coloredlogs~=15.0.0
Requires-Dist: markdown2~=2.5.0
Provides-Extra: dev
Requires-Dist: cibuildwheel; extra == "dev"
